gen_pdf_abc_xyz_will_change_later/__init__.py
gen_pdf_abc_xyz_will_change_later/document.py
gen_pdf_abc_xyz_will_change_later/page.py
gen_pdf_abc_xyz_will_change_later/blocks/__init__.py
gen_pdf_abc_xyz_will_change_later/blocks/base.py
gen_pdf_abc_xyz_will_change_later/blocks/columns.py
gen_pdf_abc_xyz_will_change_later/blocks/container.py
gen_pdf_abc_xyz_will_change_later/blocks/grid.py
gen_pdf_abc_xyz_will_change_later/blocks/icon.py
gen_pdf_abc_xyz_will_change_later/blocks/image.py
gen_pdf_abc_xyz_will_change_later/blocks/lucide.py
gen_pdf_abc_xyz_will_change_later/blocks/row.py
gen_pdf_abc_xyz_will_change_later/blocks/spacer.py
gen_pdf_abc_xyz_will_change_later/blocks/table.py
gen_pdf_abc_xyz_will_change_later/blocks/text.py
gen_pdf_abc_xyz_will_change_later/fonts/DMSans-Bold.ttf
gen_pdf_abc_xyz_will_change_later/fonts/DMSans-Regular.ttf
gen_pdf_abc_xyz_will_change_later/fonts/Lato-Regular.ttf
gen_pdf_abc_xyz_will_change_later/fonts/Montserrat-Regular.ttf
gen_pdf_abc_xyz_will_change_later/fonts/OpenSans-Regular.ttf
gen_pdf_abc_xyz_will_change_later/fonts/Poppins-Regular.ttf
gen_pdf_abc_xyz_will_change_later/fonts/Roboto-Regular.ttf
gen_pdf_abc_xyz_will_change_later/styles/__init__.py
gen_pdf_abc_xyz_will_change_later/styles/base.py
gen_pdf_abc_xyz_will_change_later/styles/box.py
gen_pdf_abc_xyz_will_change_later/styles/context.py
gen_pdf_abc_xyz_will_change_later/styles/icon.py
gen_pdf_abc_xyz_will_change_later/styles/text.py
pdf_abc_this_will_change-0.1.9.dist-info/licenses/LICENSE
pdf_abc_this_will_change-0.1.9.dist-info/METADATA
pdf_abc_this_will_change-0.1.9.dist-info/WHEEL
pdf_abc_this_will_change-0.1.9.dist-info/top_level.txt
pdf_abc_this_will_change-0.1.9.dist-info/RECORD
