Metadata-Version: 2.4
Name: pdf-abc-this-will-change
Version: 0.1.9
Summary: PDF Generation Library
Author: Try3D
Project-URL: Homepage, https://github.com/try3d/gen-pdf
Project-URL: Bug Tracker, https://github.com/try3d/gen-pdf/issues
Classifier: Programming Language :: Python :: 3
Classifier: Operating System :: OS Independent
Requires-Python: >=3.7
License-File: LICENSE
Requires-Dist: charset-normalizer>=3.0.0
Requires-Dist: pillow>=10.0.0
Requires-Dist: reportlab>=4.0.0
Dynamic: license-file
